MANIFEST.in
README.md
README.rst
setup.cfg
setup.py
esgfpid/__init__.py
esgfpid/check.py
esgfpid/connector.py
esgfpid/coupling.py
esgfpid/defaults.py
esgfpid/example_usage.py
esgfpid/exceptions.py
esgfpid.egg-info/PKG-INFO
esgfpid.egg-info/SOURCES.txt
esgfpid.egg-info/dependency_links.txt
esgfpid.egg-info/not-zip-safe
esgfpid.egg-info/requires.txt
esgfpid.egg-info/top_level.txt
esgfpid/assistant/__init__.py
esgfpid/assistant/consistency.py
esgfpid/assistant/datacart.py
esgfpid/assistant/errata.py
esgfpid/assistant/messages.py
esgfpid/assistant/publish.py
esgfpid/assistant/unpublish.py
esgfpid/rabbit/__init__.py
esgfpid/rabbit/exceptions.py
esgfpid/rabbit/naturalsorting.py
esgfpid/rabbit/nodemanager.py
esgfpid/rabbit/rabbit.py
esgfpid/rabbit/rabbitutils.py
esgfpid/rabbit/asynchronous/__init__.py
esgfpid/rabbit/asynchronous/asynchronous.py
esgfpid/rabbit/asynchronous/exceptions.py
esgfpid/rabbit/asynchronous/rabbitthread.py
esgfpid/rabbit/asynchronous/thread_builder.py
esgfpid/rabbit/asynchronous/thread_confirmer.py
esgfpid/rabbit/asynchronous/thread_feeder.py
esgfpid/rabbit/asynchronous/thread_returnhandler.py
esgfpid/rabbit/asynchronous/thread_shutter.py
esgfpid/rabbit/asynchronous/thread_statemachine.py
esgfpid/rabbit/synchronous/__init__.py
esgfpid/rabbit/synchronous/synchronous.py
esgfpid/solr/__init__.py
esgfpid/solr/serverconnector.py
esgfpid/solr/solr.py
esgfpid/solr/tasks/__init__.py
esgfpid/solr/tasks/all_versions_of_dataset.py
esgfpid/solr/tasks/filehandles_same_dataset.py
esgfpid/solr/tasks/utils.py
esgfpid/utils/__init__.py
esgfpid/utils/allutils.py
esgfpid/utils/argsutils.py
esgfpid/utils/error_message_utils.py
esgfpid/utils/handleutils.py
esgfpid/utils/logutils.py
esgfpid/utils/miscutils.py
esgfpid/utils/routingkeys.py
esgfpid/utils/timeutils.py
tests/__init__.py
tests/globalvar.py
tests/littletest.py
tests/littletest_fallbackexchange.py
tests/littletest_forcefinish_during_reconnect.py
tests/littletest_nonstring_exchange.py
tests/littletest_rabbitshutdown.py
tests/main_test_script.py
tests/rabbitmqtest.py
tests/resources/TESTVALUES.py
tests/resources/__init__.py
tests/resources/error_messages.py
tests/resources/pikamock.py
