Metadata-Version: 1.1
Name: esgfpid
Version: 0.8.2
Summary: Library for sending PID requests to a rabbit messaging queue during ESGF publication.
Home-page: https://github.com/IS-ENES-Data/esgf-pid
Author: Merret Buurman, German Climate Computing Centre (DKRZ)
Author-email: buurman@dkrz.de
License: UNKNOWN
Download-URL: https://github.com/IS-ENES-Data/esgf-pid/archive/0.8.0.tar.gz
Platform: UNKNOWN
Classifier: Development Status :: 4 - Beta
Classifier: Programming Language :: Python :: 2
Classifier: Programming Language :: Python :: 2.7
Classifier: Programming Language :: Python :: 3.7
Classifier: License :: OSI Approved :: Apache Software License
Classifier: Intended Audience :: Developers
Classifier: Topic :: Software Development :: Libraries :: Python Modules
